AUTHORS
INSTALL
LICENSE
MANIFEST.in
README
fabfile.py
requirements.txt
setup.cfg
setup.py
Fabric_with_working_dependencies.egg-info/PKG-INFO
Fabric_with_working_dependencies.egg-info/SOURCES.txt
Fabric_with_working_dependencies.egg-info/dependency_links.txt
Fabric_with_working_dependencies.egg-info/entry_points.txt
Fabric_with_working_dependencies.egg-info/requires.txt
Fabric_with_working_dependencies.egg-info/top_level.txt
docs/development.rst
docs/faq.rst
docs/index.rst
docs/installation.rst
docs/tutorial.rst
docs/api/contrib/console.rst
docs/api/contrib/django.rst
docs/api/contrib/files.rst
docs/api/contrib/project.rst
docs/api/core/colors.rst
docs/api/core/context_managers.rst
docs/api/core/decorators.rst
docs/api/core/network.rst
docs/api/core/operations.rst
docs/api/core/utils.rst
docs/changes/0.9.1.rst
docs/changes/0.9.2.rst
docs/changes/0.9.3.rst
docs/changes/0.9.4.rst
docs/changes/0.9.5.rst
docs/changes/0.9.rst
docs/changes/1.0.1.rst
docs/changes/1.0.rst
docs/usage/env.rst
docs/usage/execution.rst
docs/usage/fab.rst
docs/usage/fabfiles.rst
docs/usage/interactivity.rst
docs/usage/library.rst
docs/usage/output_controls.rst
docs/usage/ssh.rst
fabric/__init__.py
fabric/api.py
fabric/auth.py
fabric/colors.py
fabric/context_managers.py
fabric/decorators.py
fabric/io.py
fabric/main.py
fabric/network.py
fabric/operations.py
fabric/sftp.py
fabric/state.py
fabric/thread_handling.py
fabric/utils.py
fabric/version.py
fabric/contrib/__init__.py
fabric/contrib/console.py
fabric/contrib/django.py
fabric/contrib/files.py
fabric/contrib/project.py
tests/Python26SocketServer.py
tests/fake_filesystem.py
tests/server.py
tests/test_context_managers.py
tests/test_decorators.py
tests/test_main.py
tests/test_network.py
tests/test_operations.py
tests/test_server.py
tests/test_state.py
tests/test_utils.py
tests/test_version.py
tests/utils.py